[
    {
        "bank_soal_id": "42",
        "soal_id": "2241",
        "nis": "242507004",
        "jawaban": "a",
        "kunci_jawaban": "a",
        "nilai": "1.00",
        "register_user": "242507004",
        "register_date": "2025-10-09 12:10:50",
        "update_user": "242507004",
        "update_date": "2025-10-09 12:10:50",
        "jml_soal": "45",
        "bobot_nilai": "1"
    },
    {
        "bank_soal_id": "42",
        "soal_id": "2242",
        "nis": "242507004",
        "jawaban": "a",
        "kunci_jawaban": "a",
        "nilai": "1.00",
        "register_user": "242507004",
        "register_date": "2025-10-09 12:11:04",
        "update_user": "242507004",
        "update_date": "2025-10-09 12:11:04",
        "jml_soal": "45",
        "bobot_nilai": "1"
    },
    {
        "bank_soal_id": "42",
        "soal_id": "2243",
        "nis": "242507004",
        "jawaban": "d",
        "kunci_jawaban": "d",
        "nilai": "1.00",
        "register_user": "242507004",
        "register_date": "2025-10-09 12:11:15",
        "update_user": "242507004",
        "update_date": "2025-10-09 12:11:21",
        "jml_soal": "45",
        "bobot_nilai": "1"
    },
    {
        "bank_soal_id": "42",
        "soal_id": "2244",
        "nis": "242507004",
        "jawaban": "d",
        "kunci_jawaban": "d",
        "nilai": "1.00",
        "register_user": "242507004",
        "register_date": "2025-10-09 12:12:02",
        "update_user": "242507004",
        "update_date": "2025-10-09 12:12:02",
        "jml_soal": "45",
        "bobot_nilai": "1"
    },
    {
        "bank_soal_id": "42",
        "soal_id": "2246",
        "nis": "242507004",
        "jawaban": "a",
        "kunci_jawaban": "a",
        "nilai": "1.00",
        "register_user": "242507004",
        "register_date": "2025-10-09 12:12:53",
        "update_user": "242507004",
        "update_date": "2025-10-09 12:12:53",
        "jml_soal": "45",
        "bobot_nilai": "1"
    },
    {
        "bank_soal_id": "42",
        "soal_id": "2248",
        "nis": "242507004",
        "jawaban": "a",
        "kunci_jawaban": "a",
        "nilai": "1.00",
        "register_user": "242507004",
        "register_date": "2025-10-09 12:13:53",
        "update_user": "242507004",
        "update_date": "2025-10-09 12:13:53",
        "jml_soal": "45",
        "bobot_nilai": "1"
    },
    {
        "bank_soal_id": "42",
        "soal_id": "2251",
        "nis": "242507004",
        "jawaban": "a",
        "kunci_jawaban": "a",
        "nilai": "1.00",
        "register_user": "242507004",
        "register_date": "2025-10-09 12:24:54",
        "update_user": "242507004",
        "update_date": "2025-10-09 12:24:54",
        "jml_soal": "45",
        "bobot_nilai": "1"
    },
    {
        "bank_soal_id": "42",
        "soal_id": "2252",
        "nis": "242507004",
        "jawaban": "a",
        "kunci_jawaban": "a",
        "nilai": "1.00",
        "register_user": "242507004",
        "register_date": "2025-10-09 12:18:29",
        "update_user": "242507004",
        "update_date": "2025-10-09 12:18:29",
        "jml_soal": "45",
        "bobot_nilai": "1"
    },
    {
        "bank_soal_id": "42",
        "soal_id": "2253",
        "nis": "242507004",
        "jawaban": "a",
        "kunci_jawaban": "a",
        "nilai": "1.00",
        "register_user": "242507004",
        "register_date": "2025-10-09 12:24:53",
        "update_user": "242507004",
        "update_date": "2025-10-09 12:24:53",
        "jml_soal": "45",
        "bobot_nilai": "1"
    },
    {
        "bank_soal_id": "42",
        "soal_id": "2255",
        "nis": "242507004",
        "jawaban": "c",
        "kunci_jawaban": "a",
        "nilai": "0.00",
        "register_user": "242507004",
        "register_date": "2025-10-09 12:24:39",
        "update_user": "242507004",
        "update_date": "2025-10-09 12:24:39",
        "jml_soal": "45",
        "bobot_nilai": "1"
    },
    {
        "bank_soal_id": "42",
        "soal_id": "2258",
        "nis": "242507004",
        "jawaban": "a",
        "kunci_jawaban": "a",
        "nilai": "1.00",
        "register_user": "242507004",
        "register_date": "2025-10-09 12:19:36",
        "update_user": "242507004",
        "update_date": "2025-10-09 12:19:36",
        "jml_soal": "45",
        "bobot_nilai": "1"
    },
    {
        "bank_soal_id": "42",
        "soal_id": "2260",
        "nis": "242507004",
        "jawaban": "a",
        "kunci_jawaban": "a",
        "nilai": "1.00",
        "register_user": "242507004",
        "register_date": "2025-10-09 12:25:27",
        "update_user": "242507004",
        "update_date": "2025-10-09 12:25:27",
        "jml_soal": "45",
        "bobot_nilai": "1"
    },
    {
        "bank_soal_id": "42",
        "soal_id": "2417",
        "nis": "242507004",
        "jawaban": "a",
        "kunci_jawaban": "a",
        "nilai": "1.00",
        "register_user": "242507004",
        "register_date": "2025-10-09 12:35:22",
        "update_user": "242507004",
        "update_date": "2025-10-09 12:35:22",
        "jml_soal": "45",
        "bobot_nilai": "1"
    },
    {
        "bank_soal_id": "42",
        "soal_id": "2418",
        "nis": "242507004",
        "jawaban": "a",
        "kunci_jawaban": "a",
        "nilai": "1.00",
        "register_user": "242507004",
        "register_date": "2025-10-09 12:24:27",
        "update_user": "242507004",
        "update_date": "2025-10-09 12:24:27",
        "jml_soal": "45",
        "bobot_nilai": "1"
    },
    {
        "bank_soal_id": "42",
        "soal_id": "2420",
        "nis": "242507004",
        "jawaban": "a",
        "kunci_jawaban": "a",
        "nilai": "1.00",
        "register_user": "242507004",
        "register_date": "2025-10-09 12:20:16",
        "update_user": "242507004",
        "update_date": "2025-10-09 12:20:16",
        "jml_soal": "45",
        "bobot_nilai": "1"
    },
    {
        "bank_soal_id": "42",
        "soal_id": "2422",
        "nis": "242507004",
        "jawaban": "b",
        "kunci_jawaban": "c",
        "nilai": "0.00",
        "register_user": "242507004",
        "register_date": "2025-10-09 12:44:41",
        "update_user": "242507004",
        "update_date": "2025-10-09 12:44:41",
        "jml_soal": "45",
        "bobot_nilai": "1"
    },
    {
        "bank_soal_id": "42",
        "soal_id": "2425",
        "nis": "242507004",
        "jawaban": "a",
        "kunci_jawaban": "a",
        "nilai": "1.00",
        "register_user": "242507004",
        "register_date": "2025-10-09 12:27:31",
        "update_user": "242507004",
        "update_date": "2025-10-09 12:27:31",
        "jml_soal": "45",
        "bobot_nilai": "1"
    },
    {
        "bank_soal_id": "42",
        "soal_id": "2426",
        "nis": "242507004",
        "jawaban": "a",
        "kunci_jawaban": "a",
        "nilai": "1.00",
        "register_user": "242507004",
        "register_date": "2025-10-09 12:44:45",
        "update_user": "242507004",
        "update_date": "2025-10-09 12:44:45",
        "jml_soal": "45",
        "bobot_nilai": "1"
    },
    {
        "bank_soal_id": "42",
        "soal_id": "2474",
        "nis": "242507004",
        "jawaban": "a",
        "kunci_jawaban": "a",
        "nilai": "1.00",
        "register_user": "242507004",
        "register_date": "2025-10-09 12:44:50",
        "update_user": "242507004",
        "update_date": "2025-10-09 12:44:50",
        "jml_soal": "45",
        "bobot_nilai": "1"
    },
    {
        "bank_soal_id": "42",
        "soal_id": "2489",
        "nis": "242507004",
        "jawaban": "a",
        "kunci_jawaban": "a",
        "nilai": "1.00",
        "register_user": "242507004",
        "register_date": "2025-10-09 12:57:24",
        "update_user": "242507004",
        "update_date": "2025-10-09 12:57:31",
        "jml_soal": "45",
        "bobot_nilai": "1"
    },
    {
        "bank_soal_id": "42",
        "soal_id": "2493",
        "nis": "242507004",
        "jawaban": "b",
        "kunci_jawaban": "c",
        "nilai": "0.00",
        "register_user": "242507004",
        "register_date": "2025-10-09 12:32:53",
        "update_user": "242507004",
        "update_date": "2025-10-09 12:32:53",
        "jml_soal": "45",
        "bobot_nilai": "1"
    },
    {
        "bank_soal_id": "42",
        "soal_id": "2497",
        "nis": "242507004",
        "jawaban": "a",
        "kunci_jawaban": "a",
        "nilai": "1.00",
        "register_user": "242507004",
        "register_date": "2025-10-09 12:29:58",
        "update_user": "242507004",
        "update_date": "2025-10-09 12:29:58",
        "jml_soal": "45",
        "bobot_nilai": "1"
    },
    {
        "bank_soal_id": "42",
        "soal_id": "2500",
        "nis": "242507004",
        "jawaban": "b",
        "kunci_jawaban": "b",
        "nilai": "1.00",
        "register_user": "242507004",
        "register_date": "2025-10-09 12:57:57",
        "update_user": "242507004",
        "update_date": "2025-10-09 12:57:57",
        "jml_soal": "45",
        "bobot_nilai": "1"
    },
    {
        "bank_soal_id": "42",
        "soal_id": "2502",
        "nis": "242507004",
        "jawaban": "a",
        "kunci_jawaban": "a",
        "nilai": "1.00",
        "register_user": "242507004",
        "register_date": "2025-10-09 12:45:09",
        "update_user": "242507004",
        "update_date": "2025-10-09 12:45:09",
        "jml_soal": "45",
        "bobot_nilai": "1"
    },
    {
        "bank_soal_id": "42",
        "soal_id": "2504",
        "nis": "242507004",
        "jawaban": "c",
        "kunci_jawaban": "c",
        "nilai": "1.00",
        "register_user": "242507004",
        "register_date": "2025-10-09 12:34:05",
        "update_user": "242507004",
        "update_date": "2025-10-09 12:34:05",
        "jml_soal": "45",
        "bobot_nilai": "1"
    },
    {
        "bank_soal_id": "42",
        "soal_id": "2505",
        "nis": "242507004",
        "jawaban": "b",
        "kunci_jawaban": "a",
        "nilai": "0.00",
        "register_user": "242507004",
        "register_date": "2025-10-09 12:38:01",
        "update_user": "242507004",
        "update_date": "2025-10-09 12:38:01",
        "jml_soal": "45",
        "bobot_nilai": "1"
    },
    {
        "bank_soal_id": "42",
        "soal_id": "2506",
        "nis": "242507004",
        "jawaban": "a",
        "kunci_jawaban": "a",
        "nilai": "1.00",
        "register_user": "242507004",
        "register_date": "2025-10-09 12:39:04",
        "update_user": "242507004",
        "update_date": "2025-10-09 12:39:04",
        "jml_soal": "45",
        "bobot_nilai": "1"
    },
    {
        "bank_soal_id": "42",
        "soal_id": "2507",
        "nis": "242507004",
        "jawaban": "a",
        "kunci_jawaban": "a",
        "nilai": "1.00",
        "register_user": "242507004",
        "register_date": "2025-10-09 12:39:19",
        "update_user": "242507004",
        "update_date": "2025-10-09 12:39:19",
        "jml_soal": "45",
        "bobot_nilai": "1"
    },
    {
        "bank_soal_id": "42",
        "soal_id": "2508",
        "nis": "242507004",
        "jawaban": "a",
        "kunci_jawaban": "a",
        "nilai": "1.00",
        "register_user": "242507004",
        "register_date": "2025-10-09 12:58:07",
        "update_user": "242507004",
        "update_date": "2025-10-09 12:58:07",
        "jml_soal": "45",
        "bobot_nilai": "1"
    },
    {
        "bank_soal_id": "42",
        "soal_id": "2512",
        "nis": "242507004",
        "jawaban": "a",
        "kunci_jawaban": "a",
        "nilai": "1.00",
        "register_user": "242507004",
        "register_date": "2025-10-09 12:58:44",
        "update_user": "242507004",
        "update_date": "2025-10-09 12:58:44",
        "jml_soal": "45",
        "bobot_nilai": "1"
    },
    {
        "bank_soal_id": "42",
        "soal_id": "2513",
        "nis": "242507004",
        "jawaban": "a",
        "kunci_jawaban": "a",
        "nilai": "1.00",
        "register_user": "242507004",
        "register_date": "2025-10-09 12:58:53",
        "update_user": "242507004",
        "update_date": "2025-10-09 12:58:53",
        "jml_soal": "45",
        "bobot_nilai": "1"
    },
    {
        "bank_soal_id": "42",
        "soal_id": "2514",
        "nis": "242507004",
        "jawaban": "a",
        "kunci_jawaban": "a",
        "nilai": "1.00",
        "register_user": "242507004",
        "register_date": "2025-10-09 12:59:42",
        "update_user": "242507004",
        "update_date": "2025-10-09 12:59:42",
        "jml_soal": "45",
        "bobot_nilai": "1"
    },
    {
        "bank_soal_id": "42",
        "soal_id": "2516",
        "nis": "242507004",
        "jawaban": "a",
        "kunci_jawaban": "a",
        "nilai": "1.00",
        "register_user": "242507004",
        "register_date": "2025-10-09 12:42:01",
        "update_user": "242507004",
        "update_date": "2025-10-09 12:42:01",
        "jml_soal": "45",
        "bobot_nilai": "1"
    },
    {
        "bank_soal_id": "42",
        "soal_id": "2517",
        "nis": "242507004",
        "jawaban": "a",
        "kunci_jawaban": "a",
        "nilai": "1.00",
        "register_user": "242507004",
        "register_date": "2025-10-09 12:42:45",
        "update_user": "242507004",
        "update_date": "2025-10-09 12:42:45",
        "jml_soal": "45",
        "bobot_nilai": "1"
    },
    {
        "bank_soal_id": "42",
        "soal_id": "2518",
        "nis": "242507004",
        "jawaban": "a",
        "kunci_jawaban": "a",
        "nilai": "1.00",
        "register_user": "242507004",
        "register_date": "2025-10-09 12:59:48",
        "update_user": "242507004",
        "update_date": "2025-10-09 12:59:48",
        "jml_soal": "45",
        "bobot_nilai": "1"
    },
    {
        "bank_soal_id": "42",
        "soal_id": "2519",
        "nis": "242507004",
        "jawaban": "d",
        "kunci_jawaban": "d",
        "nilai": "1.00",
        "register_user": "242507004",
        "register_date": "2025-10-09 12:43:26",
        "update_user": "242507004",
        "update_date": "2025-10-09 12:43:26",
        "jml_soal": "45",
        "bobot_nilai": "1"
    },
    {
        "bank_soal_id": "42",
        "soal_id": "2521",
        "nis": "242507004",
        "jawaban": "b",
        "kunci_jawaban": "b",
        "nilai": "1.00",
        "register_user": "242507004",
        "register_date": "2025-10-09 12:59:54",
        "update_user": "242507004",
        "update_date": "2025-10-09 12:59:54",
        "jml_soal": "45",
        "bobot_nilai": "1"
    },
    {
        "bank_soal_id": "42",
        "soal_id": "2522",
        "nis": "242507004",
        "jawaban": "a",
        "kunci_jawaban": "a",
        "nilai": "1.00",
        "register_user": "242507004",
        "register_date": "2025-10-09 12:46:20",
        "update_user": "242507004",
        "update_date": "2025-10-09 12:46:20",
        "jml_soal": "45",
        "bobot_nilai": "1"
    },
    {
        "bank_soal_id": "42",
        "soal_id": "2525",
        "nis": "242507004",
        "jawaban": "a",
        "kunci_jawaban": "a",
        "nilai": "1.00",
        "register_user": "242507004",
        "register_date": "2025-10-09 12:59:58",
        "update_user": "242507004",
        "update_date": "2025-10-09 13:00:00",
        "jml_soal": "45",
        "bobot_nilai": "1"
    },
    {
        "bank_soal_id": "42",
        "soal_id": "2528",
        "nis": "242507004",
        "jawaban": "a",
        "kunci_jawaban": "d",
        "nilai": "0.00",
        "register_user": "242507004",
        "register_date": "2025-10-09 12:47:40",
        "update_user": "242507004",
        "update_date": "2025-10-09 12:47:40",
        "jml_soal": "45",
        "bobot_nilai": "1"
    },
    {
        "bank_soal_id": "42",
        "soal_id": "2503",
        "nis": "242507004",
        "jawaban": "a",
        "kunci_jawaban": "a",
        "nilai": "1",
        "register_user": "242507004",
        "register_date": "2025-10-13 10:26:54",
        "update_user": "242507004",
        "update_date": "2025-10-13 10:26:54",
        "jml_soal": 45,
        "bobot_nilai": "1"
    },
    {
        "bank_soal_id": "42",
        "soal_id": "2515",
        "nis": "242507004",
        "jawaban": "d",
        "kunci_jawaban": "d",
        "nilai": "1",
        "register_user": "242507004",
        "register_date": "2025-10-13 10:27:01",
        "update_user": "242507004",
        "update_date": "2025-10-13 10:27:01",
        "jml_soal": 45,
        "bobot_nilai": "1"
    },
    {
        "bank_soal_id": "42",
        "soal_id": "2520",
        "nis": "242507004",
        "jawaban": "a",
        "kunci_jawaban": "a",
        "nilai": "1",
        "register_user": "242507004",
        "register_date": "2025-10-13 10:27:15",
        "update_user": "242507004",
        "update_date": "2025-10-13 10:27:15",
        "jml_soal": 45,
        "bobot_nilai": "1"
    },
    {
        "bank_soal_id": "42",
        "soal_id": "2527",
        "nis": "242507004",
        "jawaban": "a",
        "kunci_jawaban": "a",
        "nilai": "1",
        "register_user": "242507004",
        "register_date": "2025-10-13 10:27:39",
        "update_user": "242507004",
        "update_date": "2025-10-13 10:27:39",
        "jml_soal": 45,
        "bobot_nilai": "1"
    },
    {
        "bank_soal_id": "42",
        "soal_id": "3118",
        "nis": "242507004",
        "jawaban": "a",
        "kunci_jawaban": "a",
        "nilai": "1",
        "register_user": "242507004",
        "register_date": "2025-10-13 10:27:54",
        "update_user": "242507004",
        "update_date": "2025-10-13 10:27:54",
        "jml_soal": 45,
        "bobot_nilai": "1"
    }
]