[
    {
        "bank_soal_id": "35",
        "soal_id": "92",
        "nis": "242507050",
        "jawaban": "Monita",
        "kata_kunci_1": "Galang",
        "kata_kunci_2": "galang",
        "nilai": 0,
        "register_user": "242507050",
        "register_date": "2025-10-13 08:33:12",
        "update_user": "242507050",
        "update_date": "2025-10-13 08:33:12",
        "bobot_nilai": 0,
        "jml_soal": 5
    },
    {
        "bank_soal_id": "35",
        "soal_id": "83",
        "nis": "242507050",
        "jawaban": "August 17th",
        "kata_kunci_1": "August 17th",
        "kata_kunci_2": "august 17th",
        "nilai": 0,
        "register_user": "242507050",
        "register_date": "2025-10-13 08:36:24",
        "update_user": "242507050",
        "update_date": "2025-10-13 08:36:24",
        "bobot_nilai": 0,
        "jml_soal": 5
    },
    {
        "bank_soal_id": "35",
        "soal_id": "84",
        "nis": "242507050",
        "jawaban": "Independence Day",
        "kata_kunci_1": "When I was a child",
        "kata_kunci_2": "When he was a child",
        "nilai": 0,
        "register_user": "242507050",
        "register_date": "2025-10-13 08:38:34",
        "update_user": "242507050",
        "update_date": "2025-10-13 08:38:34",
        "bobot_nilai": 0,
        "jml_soal": 5
    },
    {
        "bank_soal_id": "35",
        "soal_id": "90",
        "nis": "242507050",
        "jawaban": "Happy and delighted",
        "kata_kunci_1": "delighted",
        "kata_kunci_2": "happy",
        "nilai": 0,
        "register_user": "242507050",
        "register_date": "2025-10-13 08:40:22",
        "update_user": "242507050",
        "update_date": "2025-10-13 08:40:22",
        "bobot_nilai": 0,
        "jml_soal": 5
    },
    {
        "bank_soal_id": "35",
        "soal_id": "87",
        "nis": "242507050",
        "jawaban": "Some people wore Indonesian Heroes' customes",
        "kata_kunci_1": "Indonesian heroes\u2019 costumes",
        "kata_kunci_2": "dressed like local ghosts",
        "nilai": 0,
        "register_user": "242507050",
        "register_date": "2025-10-13 08:42:07",
        "update_user": "242507050",
        "update_date": "2025-10-13 08:42:07",
        "bobot_nilai": 0,
        "jml_soal": 5
    }
]