[
    {
        "bank_soal_id": "35",
        "soal_id": "87",
        "nis": "242507058",
        "jawaban": "Kostum pahlawan Indonesia dan hantu lokal",
        "kata_kunci_1": "Indonesian heroes\u2019 costumes",
        "kata_kunci_2": "dressed like local ghosts",
        "nilai": 0,
        "register_user": "242507058",
        "register_date": "2025-10-13 09:04:38",
        "update_user": "242507058",
        "update_date": "2025-10-13 09:04:38",
        "bobot_nilai": 0,
        "jml_soal": 5
    },
    {
        "bank_soal_id": "35",
        "soal_id": "84",
        "nis": "242507058",
        "jawaban": "Saat hari kemerdekaan",
        "kata_kunci_1": "When I was a child",
        "kata_kunci_2": "When he was a child",
        "nilai": 0,
        "register_user": "242507058",
        "register_date": "2025-10-13 09:06:14",
        "update_user": "242507058",
        "update_date": "2025-10-13 09:06:14",
        "bobot_nilai": 0,
        "jml_soal": 5
    },
    {
        "bank_soal_id": "35",
        "soal_id": "90",
        "nis": "242507058",
        "jawaban": "menyenangkan",
        "kata_kunci_1": "delighted",
        "kata_kunci_2": "happy",
        "nilai": 0,
        "register_user": "242507058",
        "register_date": "2025-10-13 09:10:27",
        "update_user": "242507058",
        "update_date": "2025-10-13 09:10:27",
        "bobot_nilai": 0,
        "jml_soal": 5
    },
    {
        "bank_soal_id": "35",
        "soal_id": "83",
        "nis": "242507058",
        "jawaban": "17 August 1945",
        "kata_kunci_1": "August 17th",
        "kata_kunci_2": "august 17th",
        "nilai": 0,
        "register_user": "242507058",
        "register_date": "2025-10-13 09:12:55",
        "update_user": "242507058",
        "update_date": "2025-10-13 09:12:55",
        "bobot_nilai": 0,
        "jml_soal": 5
    },
    {
        "bank_soal_id": "35",
        "soal_id": "92",
        "nis": "242507058",
        "jawaban": "Maonita",
        "kata_kunci_1": "Galang",
        "kata_kunci_2": "galang",
        "nilai": 0,
        "register_user": "242507058",
        "register_date": "2025-10-13 09:14:02",
        "update_user": "242507058",
        "update_date": "2025-10-13 09:14:02",
        "bobot_nilai": 0,
        "jml_soal": 5
    }
]