[
    {
        "bank_soal_id": "20",
        "soal_id": "54",
        "nis": "252607044",
        "jawaban": "a",
        "kunci_jawaban": "a",
        "nilai": "1.00",
        "register_user": "252607044",
        "register_date": "2025-10-09 13:01:57",
        "update_user": "252607044",
        "update_date": "2025-10-09 13:01:57",
        "jml_soal": "45",
        "bobot_nilai": "1"
    },
    {
        "bank_soal_id": "20",
        "soal_id": "55",
        "nis": "252607044",
        "jawaban": "c",
        "kunci_jawaban": "c",
        "nilai": "1.00",
        "register_user": "252607044",
        "register_date": "2025-10-09 13:02:09",
        "update_user": "252607044",
        "update_date": "2025-10-09 13:02:18",
        "jml_soal": "45",
        "bobot_nilai": "1"
    },
    {
        "bank_soal_id": "20",
        "soal_id": "56",
        "nis": "252607044",
        "jawaban": "c",
        "kunci_jawaban": "c",
        "nilai": "1.00",
        "register_user": "252607044",
        "register_date": "2025-10-09 13:02:30",
        "update_user": "252607044",
        "update_date": "2025-10-09 13:02:30",
        "jml_soal": "45",
        "bobot_nilai": "1"
    },
    {
        "bank_soal_id": "20",
        "soal_id": "57",
        "nis": "252607044",
        "jawaban": "a",
        "kunci_jawaban": "a",
        "nilai": "1.00",
        "register_user": "252607044",
        "register_date": "2025-10-09 13:06:56",
        "update_user": "252607044",
        "update_date": "2025-10-09 13:06:56",
        "jml_soal": "45",
        "bobot_nilai": "1"
    },
    {
        "bank_soal_id": "20",
        "soal_id": "58",
        "nis": "252607044",
        "jawaban": "d",
        "kunci_jawaban": "d",
        "nilai": "1.00",
        "register_user": "252607044",
        "register_date": "2025-10-09 13:20:13",
        "update_user": "252607044",
        "update_date": "2025-10-09 13:20:13",
        "jml_soal": "45",
        "bobot_nilai": "1"
    },
    {
        "bank_soal_id": "20",
        "soal_id": "59",
        "nis": "252607044",
        "jawaban": "a",
        "kunci_jawaban": "a",
        "nilai": "1.00",
        "register_user": "252607044",
        "register_date": "2025-10-09 13:20:04",
        "update_user": "252607044",
        "update_date": "2025-10-09 13:24:17",
        "jml_soal": "45",
        "bobot_nilai": "1"
    },
    {
        "bank_soal_id": "20",
        "soal_id": "60",
        "nis": "252607044",
        "jawaban": "b",
        "kunci_jawaban": "b",
        "nilai": "1.00",
        "register_user": "252607044",
        "register_date": "2025-10-09 13:24:06",
        "update_user": "252607044",
        "update_date": "2025-10-09 13:24:06",
        "jml_soal": "45",
        "bobot_nilai": "1"
    },
    {
        "bank_soal_id": "20",
        "soal_id": "72",
        "nis": "252607044",
        "jawaban": "b",
        "kunci_jawaban": "b",
        "nilai": "1.00",
        "register_user": "252607044",
        "register_date": "2025-10-09 13:19:52",
        "update_user": "252607044",
        "update_date": "2025-10-09 13:19:59",
        "jml_soal": "45",
        "bobot_nilai": "1"
    },
    {
        "bank_soal_id": "20",
        "soal_id": "73",
        "nis": "252607044",
        "jawaban": "d",
        "kunci_jawaban": "c",
        "nilai": "0.00",
        "register_user": "252607044",
        "register_date": "2025-10-09 13:17:24",
        "update_user": "252607044",
        "update_date": "2025-10-09 13:17:24",
        "jml_soal": "45",
        "bobot_nilai": "1"
    },
    {
        "bank_soal_id": "20",
        "soal_id": "81",
        "nis": "252607044",
        "jawaban": "c",
        "kunci_jawaban": "d",
        "nilai": "0.00",
        "register_user": "252607044",
        "register_date": "2025-10-09 13:19:49",
        "update_user": "252607044",
        "update_date": "2025-10-09 13:19:49",
        "jml_soal": "45",
        "bobot_nilai": "1"
    },
    {
        "bank_soal_id": "20",
        "soal_id": "82",
        "nis": "252607044",
        "jawaban": "a",
        "kunci_jawaban": "a",
        "nilai": "1.00",
        "register_user": "252607044",
        "register_date": "2025-10-09 13:19:40",
        "update_user": "252607044",
        "update_date": "2025-10-09 13:19:40",
        "jml_soal": "45",
        "bobot_nilai": "1"
    },
    {
        "bank_soal_id": "20",
        "soal_id": "83",
        "nis": "252607044",
        "jawaban": "a",
        "kunci_jawaban": "a",
        "nilai": "1.00",
        "register_user": "252607044",
        "register_date": "2025-10-09 13:29:46",
        "update_user": "252607044",
        "update_date": "2025-10-09 13:29:46",
        "jml_soal": "45",
        "bobot_nilai": "1"
    },
    {
        "bank_soal_id": "20",
        "soal_id": "228",
        "nis": "252607044",
        "jawaban": "a",
        "kunci_jawaban": "a",
        "nilai": "1.00",
        "register_user": "252607044",
        "register_date": "2025-10-09 13:19:29",
        "update_user": "252607044",
        "update_date": "2025-10-09 13:19:29",
        "jml_soal": "45",
        "bobot_nilai": "1"
    },
    {
        "bank_soal_id": "20",
        "soal_id": "229",
        "nis": "252607044",
        "jawaban": "d",
        "kunci_jawaban": "d",
        "nilai": "1.00",
        "register_user": "252607044",
        "register_date": "2025-10-09 13:28:08",
        "update_user": "252607044",
        "update_date": "2025-10-09 13:28:08",
        "jml_soal": "45",
        "bobot_nilai": "1"
    },
    {
        "bank_soal_id": "20",
        "soal_id": "230",
        "nis": "252607044",
        "jawaban": "d",
        "kunci_jawaban": "d",
        "nilai": "1.00",
        "register_user": "252607044",
        "register_date": "2025-10-09 13:29:25",
        "update_user": "252607044",
        "update_date": "2025-10-09 13:29:25",
        "jml_soal": "45",
        "bobot_nilai": "1"
    },
    {
        "bank_soal_id": "20",
        "soal_id": "231",
        "nis": "252607044",
        "jawaban": "c",
        "kunci_jawaban": "c",
        "nilai": "1.00",
        "register_user": "252607044",
        "register_date": "2025-10-09 13:18:12",
        "update_user": "252607044",
        "update_date": "2025-10-09 13:18:12",
        "jml_soal": "45",
        "bobot_nilai": "1"
    },
    {
        "bank_soal_id": "20",
        "soal_id": "232",
        "nis": "252607044",
        "jawaban": "a",
        "kunci_jawaban": "a",
        "nilai": "1.00",
        "register_user": "252607044",
        "register_date": "2025-10-09 13:29:13",
        "update_user": "252607044",
        "update_date": "2025-10-09 13:29:17",
        "jml_soal": "45",
        "bobot_nilai": "1"
    },
    {
        "bank_soal_id": "20",
        "soal_id": "2835",
        "nis": "252607044",
        "jawaban": "c",
        "kunci_jawaban": "c",
        "nilai": "1.00",
        "register_user": "252607044",
        "register_date": "2025-10-09 13:29:30",
        "update_user": "252607044",
        "update_date": "2025-10-09 13:29:30",
        "jml_soal": "45",
        "bobot_nilai": "1"
    },
    {
        "bank_soal_id": "20",
        "soal_id": "2836",
        "nis": "252607044",
        "jawaban": "d",
        "kunci_jawaban": "d",
        "nilai": "1.00",
        "register_user": "252607044",
        "register_date": "2025-10-09 13:23:39",
        "update_user": "252607044",
        "update_date": "2025-10-09 13:23:39",
        "jml_soal": "45",
        "bobot_nilai": "1"
    },
    {
        "bank_soal_id": "20",
        "soal_id": "2837",
        "nis": "252607044",
        "jawaban": "d",
        "kunci_jawaban": "d",
        "nilai": "1.00",
        "register_user": "252607044",
        "register_date": "2025-10-09 13:23:30",
        "update_user": "252607044",
        "update_date": "2025-10-09 13:23:30",
        "jml_soal": "45",
        "bobot_nilai": "1"
    },
    {
        "bank_soal_id": "20",
        "soal_id": "2839",
        "nis": "252607044",
        "jawaban": "a",
        "kunci_jawaban": "d",
        "nilai": "1",
        "register_user": "252607044",
        "register_date": "2025-10-09 13:23:27",
        "update_user": "252607044",
        "update_date": "2025-10-09 13:23:27",
        "jml_soal": "45",
        "bobot_nilai": "1"
    },
    {
        "bank_soal_id": "20",
        "soal_id": "2840",
        "nis": "252607044",
        "jawaban": "a",
        "kunci_jawaban": "b",
        "nilai": "0.00",
        "register_user": "252607044",
        "register_date": "2025-10-09 13:47:43",
        "update_user": "252607044",
        "update_date": "2025-10-09 13:47:44",
        "jml_soal": "45",
        "bobot_nilai": "1"
    },
    {
        "bank_soal_id": "20",
        "soal_id": "2841",
        "nis": "252607044",
        "jawaban": "a",
        "kunci_jawaban": "b",
        "nilai": "0.00",
        "register_user": "252607044",
        "register_date": "2025-10-09 13:33:39",
        "update_user": "252607044",
        "update_date": "2025-10-09 13:33:39",
        "jml_soal": "45",
        "bobot_nilai": "1"
    },
    {
        "bank_soal_id": "20",
        "soal_id": "2842",
        "nis": "252607044",
        "jawaban": "a",
        "kunci_jawaban": "a",
        "nilai": "1.00",
        "register_user": "252607044",
        "register_date": "2025-10-09 13:47:49",
        "update_user": "252607044",
        "update_date": "2025-10-09 13:47:49",
        "jml_soal": "45",
        "bobot_nilai": "1"
    },
    {
        "bank_soal_id": "20",
        "soal_id": "2843",
        "nis": "252607044",
        "jawaban": "b",
        "kunci_jawaban": "b",
        "nilai": "1.00",
        "register_user": "252607044",
        "register_date": "2025-10-09 13:47:52",
        "update_user": "252607044",
        "update_date": "2025-10-09 13:47:53",
        "jml_soal": "45",
        "bobot_nilai": "1"
    },
    {
        "bank_soal_id": "20",
        "soal_id": "2844",
        "nis": "252607044",
        "jawaban": "a",
        "kunci_jawaban": "a",
        "nilai": "1.00",
        "register_user": "252607044",
        "register_date": "2025-10-09 13:48:03",
        "update_user": "252607044",
        "update_date": "2025-10-09 13:48:03",
        "jml_soal": "45",
        "bobot_nilai": "1"
    },
    {
        "bank_soal_id": "20",
        "soal_id": "2845",
        "nis": "252607044",
        "jawaban": "c",
        "kunci_jawaban": "c",
        "nilai": "1.00",
        "register_user": "252607044",
        "register_date": "2025-10-09 13:48:22",
        "update_user": "252607044",
        "update_date": "2025-10-09 13:48:22",
        "jml_soal": "45",
        "bobot_nilai": "1"
    },
    {
        "bank_soal_id": "20",
        "soal_id": "2846",
        "nis": "252607044",
        "jawaban": "a",
        "kunci_jawaban": "a",
        "nilai": "1.00",
        "register_user": "252607044",
        "register_date": "2025-10-09 13:48:27",
        "update_user": "252607044",
        "update_date": "2025-10-09 13:48:27",
        "jml_soal": "45",
        "bobot_nilai": "1"
    },
    {
        "bank_soal_id": "20",
        "soal_id": "2847",
        "nis": "252607044",
        "jawaban": "b",
        "kunci_jawaban": "b",
        "nilai": "1.00",
        "register_user": "252607044",
        "register_date": "2025-10-09 13:48:35",
        "update_user": "252607044",
        "update_date": "2025-10-09 13:48:35",
        "jml_soal": "45",
        "bobot_nilai": "1"
    },
    {
        "bank_soal_id": "20",
        "soal_id": "2848",
        "nis": "252607044",
        "jawaban": "a",
        "kunci_jawaban": "a",
        "nilai": "1.00",
        "register_user": "252607044",
        "register_date": "2025-10-09 13:48:40",
        "update_user": "252607044",
        "update_date": "2025-10-09 13:48:40",
        "jml_soal": "45",
        "bobot_nilai": "1"
    },
    {
        "bank_soal_id": "20",
        "soal_id": "2849",
        "nis": "252607044",
        "jawaban": "b",
        "kunci_jawaban": "b",
        "nilai": "1.00",
        "register_user": "252607044",
        "register_date": "2025-10-09 13:48:46",
        "update_user": "252607044",
        "update_date": "2025-10-09 13:48:46",
        "jml_soal": "45",
        "bobot_nilai": "1"
    },
    {
        "bank_soal_id": "20",
        "soal_id": "2850",
        "nis": "252607044",
        "jawaban": "a",
        "kunci_jawaban": "a",
        "nilai": "1.00",
        "register_user": "252607044",
        "register_date": "2025-10-09 13:48:52",
        "update_user": "252607044",
        "update_date": "2025-10-09 13:48:52",
        "jml_soal": "45",
        "bobot_nilai": "1"
    },
    {
        "bank_soal_id": "20",
        "soal_id": "2851",
        "nis": "252607044",
        "jawaban": "a",
        "kunci_jawaban": "c",
        "nilai": "0.00",
        "register_user": "252607044",
        "register_date": "2025-10-09 13:49:08",
        "update_user": "252607044",
        "update_date": "2025-10-09 13:49:08",
        "jml_soal": "45",
        "bobot_nilai": "1"
    },
    {
        "bank_soal_id": "20",
        "soal_id": "2852",
        "nis": "252607044",
        "jawaban": "b",
        "kunci_jawaban": "b",
        "nilai": "1.00",
        "register_user": "252607044",
        "register_date": "2025-10-09 13:49:15",
        "update_user": "252607044",
        "update_date": "2025-10-09 13:49:15",
        "jml_soal": "45",
        "bobot_nilai": "1"
    },
    {
        "bank_soal_id": "20",
        "soal_id": "2853",
        "nis": "252607044",
        "jawaban": "d",
        "kunci_jawaban": "d",
        "nilai": "1.00",
        "register_user": "252607044",
        "register_date": "2025-10-09 13:49:24",
        "update_user": "252607044",
        "update_date": "2025-10-09 13:49:24",
        "jml_soal": "45",
        "bobot_nilai": "1"
    },
    {
        "bank_soal_id": "20",
        "soal_id": "2854",
        "nis": "252607044",
        "jawaban": "d",
        "kunci_jawaban": "b",
        "nilai": "0.00",
        "register_user": "252607044",
        "register_date": "2025-10-09 13:49:36",
        "update_user": "252607044",
        "update_date": "2025-10-09 13:49:36",
        "jml_soal": "45",
        "bobot_nilai": "1"
    },
    {
        "bank_soal_id": "20",
        "soal_id": "2855",
        "nis": "252607044",
        "jawaban": "b",
        "kunci_jawaban": "a",
        "nilai": "0.00",
        "register_user": "252607044",
        "register_date": "2025-10-09 13:49:52",
        "update_user": "252607044",
        "update_date": "2025-10-09 13:49:52",
        "jml_soal": "45",
        "bobot_nilai": "1"
    },
    {
        "bank_soal_id": "20",
        "soal_id": "2857",
        "nis": "252607044",
        "jawaban": "d",
        "kunci_jawaban": "d",
        "nilai": "1",
        "register_user": "252607044",
        "register_date": "2025-10-13 12:49:43",
        "update_user": "252607044",
        "update_date": "2025-10-13 12:49:43",
        "jml_soal": 45,
        "bobot_nilai": "1"
    },
    {
        "bank_soal_id": "20",
        "soal_id": "2856",
        "nis": "252607044",
        "jawaban": "d",
        "kunci_jawaban": "d",
        "nilai": "1",
        "register_user": "252607044",
        "register_date": "2025-10-13 12:49:47",
        "update_user": "252607044",
        "update_date": "2025-10-13 12:49:47",
        "jml_soal": 45,
        "bobot_nilai": "1"
    },
    {
        "bank_soal_id": "20",
        "soal_id": "2858",
        "nis": "252607044",
        "jawaban": "b",
        "kunci_jawaban": "b",
        "nilai": "1",
        "register_user": "252607044",
        "register_date": "2025-10-13 12:52:19",
        "update_user": "252607044",
        "update_date": "2025-10-13 12:52:19",
        "jml_soal": 45,
        "bobot_nilai": "1"
    },
    {
        "bank_soal_id": "20",
        "soal_id": "2859",
        "nis": "252607044",
        "jawaban": "b",
        "kunci_jawaban": "b",
        "nilai": "1",
        "register_user": "252607044",
        "register_date": "2025-10-13 12:52:59",
        "update_user": "252607044",
        "update_date": "2025-10-13 12:52:59",
        "jml_soal": 45,
        "bobot_nilai": "1"
    },
    {
        "bank_soal_id": "20",
        "soal_id": "2860",
        "nis": "252607044",
        "jawaban": "d",
        "kunci_jawaban": "d",
        "nilai": "1",
        "register_user": "252607044",
        "register_date": "2025-10-13 12:53:06",
        "update_user": "252607044",
        "update_date": "2025-10-13 12:53:06",
        "jml_soal": 45,
        "bobot_nilai": "1"
    },
    {
        "bank_soal_id": "20",
        "soal_id": "2861",
        "nis": "252607044",
        "jawaban": "a",
        "kunci_jawaban": "a",
        "nilai": "1",
        "register_user": "252607044",
        "register_date": "2025-10-13 12:53:14",
        "update_user": "252607044",
        "update_date": "2025-10-13 12:53:14",
        "jml_soal": 45,
        "bobot_nilai": "1"
    },
    {
        "bank_soal_id": "20",
        "soal_id": "2862",
        "nis": "252607044",
        "jawaban": "b",
        "kunci_jawaban": "d",
        "nilai": 0,
        "register_user": "252607044",
        "register_date": "2025-10-13 12:55:17",
        "update_user": "252607044",
        "update_date": "2025-10-13 12:55:17",
        "jml_soal": 45,
        "bobot_nilai": "1"
    },
    {
        "bank_soal_id": "20",
        "soal_id": "2838",
        "nis": "252607044",
        "jawaban": "d",
        "kunci_jawaban": "b",
        "nilai": 0,
        "register_user": "252607044",
        "register_date": "2025-10-13 12:56:31",
        "update_user": "252607044",
        "update_date": "2025-10-13 12:56:31",
        "jml_soal": 45,
        "bobot_nilai": "1"
    }
]