[
    {
        "bank_soal_id": "80",
        "soal_id": "200",
        "nis": "252607032",
        "jawaban": "produksi ",
        "kata_kunci_1": "Produksi",
        "kata_kunci_2": "produksi",
        "nilai": "3.00",
        "register_user": "252607032",
        "register_date": "2025-10-09 12:37:06",
        "update_user": "252607032",
        "update_date": "2025-10-09 12:37:06",
        "bobot_nilai": "3",
        "jml_soal": "5"
    },
    {
        "bank_soal_id": "80",
        "soal_id": "201",
        "nis": "252607032",
        "jawaban": "dua tempat ibadah saling berjejer ",
        "kata_kunci_1": "Akulturasi",
        "kata_kunci_2": "akulturasi",
        "nilai": "0.00",
        "register_user": "252607032",
        "register_date": "2025-10-09 12:49:06",
        "update_user": "252607032",
        "update_date": "2025-10-09 12:49:20",
        "bobot_nilai": "3",
        "jml_soal": "5"
    },
    {
        "bank_soal_id": "80",
        "soal_id": "202",
        "nis": "252607032",
        "jawaban": "sejarah ",
        "kata_kunci_1": "SEJARAH",
        "kata_kunci_2": "Sejarah",
        "nilai": "3.00",
        "register_user": "252607032",
        "register_date": "2025-10-09 12:47:07",
        "update_user": "252607032",
        "update_date": "2025-10-09 18:20:55",
        "bobot_nilai": "3",
        "jml_soal": "5"
    },
    {
        "bank_soal_id": "80",
        "soal_id": "203",
        "nis": "252607032",
        "jawaban": "tulisan ",
        "kata_kunci_1": "Tertulis",
        "kata_kunci_2": "Tulisan",
        "nilai": "3.00",
        "register_user": "252607032",
        "register_date": "2025-10-09 12:49:30",
        "update_user": "252607032",
        "update_date": "2025-10-09 12:49:34",
        "bobot_nilai": "3",
        "jml_soal": "5"
    },
    {
        "bank_soal_id": "80",
        "soal_id": "308",
        "nis": "252607032",
        "jawaban": "monumen ",
        "kata_kunci_1": "Benda",
        "kata_kunci_2": "Artefak",
        "nilai": 0,
        "register_user": "252607032",
        "register_date": "2025-10-09 12:49:43",
        "update_user": "252607032",
        "update_date": "2025-10-09 12:50:03",
        "bobot_nilai": "3",
        "jml_soal": "5"
    }
]